invoke_common_tasks/__init__.py
invoke_common_tasks/tasks.py
invoke_common_tasks/utils/__init__.py
invoke_common_tasks/utils/config.py
invoke_common_tasks/utils/git.py
invoke_common_tasks/utils/poetry.py
invoke_common_tasks-0.4.0.dist-info/LICENSE
invoke_common_tasks-0.4.0.dist-info/METADATA
invoke_common_tasks-0.4.0.dist-info/WHEEL
invoke_common_tasks-0.4.0.dist-info/RECORD
