Metadata-Version: 2.1
Name: invoke-common-tasks
Version: 0.4.0
Summary: Some common tasks for PyInvoke to bootstrap your code quality and testing workflows.
Home-page: https://github.com/neozenith/invoke-common-tasks
License: MIT
Author: Josh Peak
Author-email: neozenith.dev@gmail.com
Requires-Python: >=3.8,<4.0
Classifier: License :: OSI Approved :: MIT License
Classifier: Programming Language :: Python :: 3
Classifier: Programming Language :: Python :: 3.8
Classifier: Programming Language :: Python :: 3.9
Classifier: Programming Language :: Python :: 3.10
Classifier: Programming Language :: Python :: 3.11
Provides-Extra: all
Provides-Extra: format
Provides-Extra: lint
Provides-Extra: test
Provides-Extra: typecheck
Requires-Dist: black (>=22.1.0,<23.0.0) ; extra == "format" or extra == "all"
Requires-Dist: coverage[toml] (>=6.3.2,<7.0.0) ; extra == "test" or extra == "all"
Requires-Dist: flake8 (>=4.0.1,<5.0.0) ; extra == "lint" or extra == "all"
Requires-Dist: flake8-docstrings (>=1.6.0,<2.0.0) ; extra == "lint" or extra == "all"
Requires-Dist: invoke (>=2.0.0,<=3.0.0)
Requires-Dist: isort (>=5.10.1,<6.0.0) ; extra == "format" or extra == "all"
Requires-Dist: mypy (>=0.942,<0.943) ; extra == "typecheck" or extra == "all"
Requires-Dist: poetry (>=1.5.1,<2.0.0)
Requires-Dist: poetry-core (>=1.6.0,<2.0.0)
Requires-Dist: pytest (>=7.1.1,<8.0.0) ; extra == "test" or extra == "all"
Requires-Dist: pytest-cov (>=3.0.0,<4.0.0) ; extra == "test" or extra == "all"
Requires-Dist: types-invoke (>=2.0.0,<=3.0.0)
Project-URL: Repository, https://github.com/neozenith/invoke-common-tasks
